.coveragerc
.gitignore
.travis.yml
LICENSE.md
LICENSE.mirumee.md
MANIFEST.in
README.md
setup.cfg
setup.py
tox.ini
tests/test_paydirekt.py
web_payments_paydirekt/__init__.py
web_payments_paydirekt.egg-info/PKG-INFO
web_payments_paydirekt.egg-info/SOURCES.txt
web_payments_paydirekt.egg-info/dependency_links.txt
web_payments_paydirekt.egg-info/requires.txt
web_payments_paydirekt.egg-info/top_level.txt
web_payments_paydirekt.egg-info/zip-safe